{".class": "MypyFile", "_fullname": "findMaxConsecutiveOnes", "is_partial_stub_package": false, "is_stub": false, "names": {".class": "SymbolTable", "List": {".class": "SymbolTableNode", "cross_ref": "typing.List", "kind": "Gdef"}, "Solution": {".class": "SymbolTableNode", "kind": "Gdef", "node": {".class": "TypeInfo", "_promote": null, "abstract_attributes": [], "bases": ["builtins.object"], "declared_metaclass": null, "defn": {".class": "ClassDef", "fullname": "findMaxConsecutiveOnes.Solution", "name": "Solution", "type_vars": []}, "flags": [], "fullname": "findMaxConsecutiveOnes.Solution", "metaclass_type": null, "metadata": {}, "module_name": "findMaxConsecutiveOnes", "mro": ["findMaxConsecutiveOnes.Solution", "builtins.object"], "names": {".class": "SymbolTable", "findMaxConsecutiveOnes_solution_one": {".class": "SymbolTableNode", "kind": "Mdef", "node": {".class": "FuncDef", "arg_kinds": [0, 0], "arg_names": ["self", "nums"], "flags": [], "fullname": "findMaxConsecutiveOnes.Solution.findMaxConsecutiveOnes_solution_one", "name": "findMaxConsecutiveOnes_solution_one", "type": {".class": "CallableType", "arg_kinds": [0, 0], "arg_names": ["self", "nums"], "arg_types": ["findMaxConsecutiveOnes.Solution", {".class": "Instance", "args": ["builtins.int"], "type_ref": "builtins.list"}], "bound_args": [], "def_extras": {"first_arg": "self"}, "fallback": "builtins.function", "implicit": false, "is_ellipsis_args": false, "name": "findMaxConsecutiveOnes_solution_one of Solution", "ret_type": "builtins.int", "variables": []}}}}, "tuple_type": null, "type_vars": [], "typeddict_type": null}}, "__doc__": {".class": "SymbolTableNode", "kind": "Gdef", "node": {".class": "Var", "flags": ["is_ready"], "fullname": "findMaxConsecutiveOnes.__doc__", "name": "__doc__", "type": "builtins.str"}}, "__file__": {".class": "SymbolTableNode", "kind": "Gdef", "node": {".class": "Var", "flags": ["is_ready"], "fullname": "findMaxConsecutiveOnes.__file__", "name": "__file__", "type": "builtins.str"}}, "__name__": {".class": "SymbolTableNode", "kind": "Gdef", "node": {".class": "Var", "flags": ["is_ready"], "fullname": "findMaxConsecutiveOnes.__name__", "name": "__name__", "type": "builtins.str"}}, "__package__": {".class": "SymbolTableNode", "kind": "Gdef", "node": {".class": "Var", "flags": ["is_ready"], "fullname": "findMaxConsecutiveOnes.__package__", "name": "__package__", "type": "builtins.str"}}, "nums": {".class": "SymbolTableNode", "kind": "Gdef", "node": {".class": "Var", "flags": [], "fullname": "findMaxConsecutiveOnes.nums", "name": "nums", "type": {".class": "Instance", "args": ["builtins.int"], "type_ref": "builtins.list"}}}, "solution": {".class": "SymbolTableNode", "kind": "Gdef", "node": {".class": "Var", "flags": [], "fullname": "findMaxConsecutiveOnes.solution", "name": "solution", "type": "findMaxConsecutiveOnes.Solution"}}, "solution_one_result": {".class": "SymbolTableNode", "kind": "Gdef", "node": {".class": "Var", "flags": [], "fullname": "findMaxConsecutiveOnes.solution_one_result", "name": "solution_one_result", "type": "builtins.int"}}}, "path": "/Users/starlord1711/Documents/Problem_Solving/Leetcode/Arrays_101/findMaxConsecutiveOnes.py"}